ubigeo_peru/__init__.py
ubigeo_peru/builder.py
ubigeo_peru/loader.py
ubigeo_peru-0.1.3.dist-info/METADATA
ubigeo_peru-0.1.3.dist-info/WHEEL
ubigeo_peru-0.1.3.dist-info/top_level.txt
ubigeo_peru-0.1.3.dist-info/RECORD
