Metadata-Version: 2.1
Name: ubigeo-peru
Version: 0.1.3
Summary: Paquete para acceder a datos de UBIGEO de Perú
Home-page: https://github.com/tuusuario/ubigeo-peru
Author: Elmer Yujra Condori
Author-email: elmerjk.20@gmail.com
Classifier: Programming Language :: Python :: 3
Classifier: License :: OSI Approved :: MIT License
Classifier: Operating System :: OS Independent
Requires-Python: >=3.6
